sheets.py
sqlConverter.py
sqlLibraryNabeel-0.0.1.dist-info/METADATA
sqlLibraryNabeel-0.0.1.dist-info/WHEEL
sqlLibraryNabeel-0.0.1.dist-info/top_level.txt
sqlLibraryNabeel-0.0.1.dist-info/RECORD
