Metadata-Version: 2.1
Name: sqlLibraryNabeel
Version: 0.0.1
Summary: Process json and convert it into dataframes
Home-page: https://github.com/#
Author: Rusab Naeem
Author-email: rusab.khan@lyftron.com
License: UNKNOWN
Platform: UNKNOWN
Requires-Dist: autopep8 (~=1.5.4)
Requires-Dist: cachetools (~=4.1.1)
Requires-Dist: certifi (~=2020.6.20)
Requires-Dist: chardet (~=3.0.4)
Requires-Dist: click (~=7.1.2)
Requires-Dist: colorama (~=0.4.4)
Requires-Dist: Flask (~=1.1.2)
Requires-Dist: google-api-core (~=1.23.0)
Requires-Dist: google-api-python-client (~=1.12.5)
Requires-Dist: google-auth (~=1.23.0)
Requires-Dist: google-auth-httplib2 (~=0.0.4)
Requires-Dist: google-auth-oauthlib (~=0.4.2)
Requires-Dist: googleapis-common-protos (~=1.52.0)
Requires-Dist: gspread (~=3.6.0)
Requires-Dist: httplib2 (~=0.18.1)
Requires-Dist: idna (~=2.10)
Requires-Dist: isort (~=5.6.4)
Requires-Dist: itsdangerous (~=1.1.0)
Requires-Dist: Jinja2 (~=2.11.2)
Requires-Dist: lazy-object-proxy (~=1.4.3)
Requires-Dist: MarkupSafe (~=1.1.1)
Requires-Dist: mccabe (~=0.6.1)
Requires-Dist: numpy (~=1.19.3)
Requires-Dist: oauth2client (~=4.1.3)
Requires-Dist: oauthlib (~=3.1.0)
Requires-Dist: pandas (~=1.1.4)
Requires-Dist: pandasql (~=0.7.3)
Requires-Dist: protobuf (~=3.13.0)
Requires-Dist: pyasn1 (~=0.4.8)
Requires-Dist: pyasn1-modules (~=0.2.8)
Requires-Dist: pycodestyle (~=2.6.0)
Requires-Dist: pylint (~=2.6.0)
Requires-Dist: python-dateutil (~=2.8.1)
Requires-Dist: pytz (~=2020.1)
Requires-Dist: requests (~=2.24.0)
Requires-Dist: requests-oauthlib (~=1.3.0)
Requires-Dist: rsa (~=4.6)
Requires-Dist: Sheets (~=0.6)
Requires-Dist: six (~=1.15.0)
Requires-Dist: SQLAlchemy (~=1.3.20)
Requires-Dist: toml (~=0.10.2)
Requires-Dist: Unidecode (~=1.1.1)
Requires-Dist: uritemplate (~=3.0.1)
Requires-Dist: urllib3 (~=1.25.11)
Requires-Dist: Werkzeug (~=1.0.1)
Requires-Dist: wrapt (~=1.12.1)
